lywsd02/__init__.py
lywsd02/client.py
lywsd02/decorators.py
lywsd02-0.0.9.dist-info/LICENSE
lywsd02-0.0.9.dist-info/METADATA
lywsd02-0.0.9.dist-info/WHEEL
lywsd02-0.0.9.dist-info/top_level.txt
lywsd02-0.0.9.dist-info/RECORD
