Metadata-Version: 2.1
Name: lywsd02
Version: 0.0.9
Summary: Lywsd02 BLE sendor Library
Home-page: https://github.com/h4/lywsd02
Author: h4
Author-email: mikhail.baranov@gmail.com
License: MIT
Platform: UNKNOWN
Classifier: Programming Language :: Python :: 3.7
Requires-Dist: bluepy (==1.3.0)
